setup.py
tsmt_distributions/Binomialdistribution.py
tsmt_distributions/Gaussiandistribution.py
tsmt_distributions/Generaldistribution.py
tsmt_distributions/__init__.py
tsmt_distributions.egg-info/PKG-INFO
tsmt_distributions.egg-info/SOURCES.txt
tsmt_distributions.egg-info/dependency_links.txt
tsmt_distributions.egg-info/not-zip-safe
tsmt_distributions.egg-info/top_level.txt