Metadata-Version: 1.0
Name: tsmt-distributions
Version: 0.1
Summary: Gaussian and Binomial distributions
Home-page: UNKNOWN
Author: Taslim Mahbub
Author-email: taslimmahbub@hotmail.com
License: UNKNOWN
Platform: UNKNOWN
